core/__init__.py
core/ad_filter.py
core/android.py
core/automation.py
core/cli.py
core/config_manager.py
core/control_flow.py
core/device_manager.py
core/emulator.py
core/exceptions.py
core/expressions.py
core/logging_config.py
core/variables.py
core/cloud/__init__.py
core/cloud/aws.py
core/cloud/base.py
core/cloud/firebase.py
core/cloud/models.py
dittomation-1.0.0.dist-info/licenses/LICENSE
recorder/__init__.py
recorder/adb_wrapper.py
recorder/element_matcher.py
recorder/event_listener.py
recorder/gesture_classifier.py
recorder/interactive_recorder.py
recorder/main.py
recorder/ui_dumper.py
recorder/workflow.py
replayer/__init__.py
replayer/executor.py
replayer/locator.py
replayer/main.py
replayer/nl_runner.py
replayer/text_runner.py
dittomation-1.0.0.dist-info/METADATA
dittomation-1.0.0.dist-info/WHEEL
dittomation-1.0.0.dist-info/entry_points.txt
dittomation-1.0.0.dist-info/top_level.txt
dittomation-1.0.0.dist-info/RECORD
