Metadata-Version: 2.4
Name: dittomation
Version: 1.0.0
Summary: Android automation made simple - record, replay, and control Android devices
Author: DittoMation Team
License: MIT
Project-URL: Homepage, https://github.com/OmPrakashSingh1704/DittoMation
Project-URL: Repository, https://github.com/OmPrakashSingh1704/DittoMation
Project-URL: Documentation, https://github.com/OmPrakashSingh1704/DittoMation#readme
Project-URL: Changelog, https://github.com/OmPrakashSingh1704/DittoMation/blob/main/CHANGELOG.md
Project-URL: Issues, https://github.com/OmPrakashSingh1704/DittoMation/issues
Keywords: android,automation,adb,testing,mobile
Classifier: Development Status :: 4 - Beta
Classifier: Environment :: Console
Classifier: Intended Audience :: Developers
Classifier: License :: OSI Approved :: MIT License
Classifier: Operating System :: OS Independent
Classifier: Programming Language :: Python :: 3
Classifier: Programming Language :: Python :: 3.8
Classifier: Programming Language :: Python :: 3.9
Classifier: Programming Language :: Python :: 3.10
Classifier: Programming Language :: Python :: 3.11
Classifier: Programming Language :: Python :: 3.12
Classifier: Programming Language :: Python :: 3.13
Classifier: Topic :: Software Development :: Testing
Classifier: Topic :: System :: Hardware :: Hardware Drivers
Classifier: Typing :: Typed
Requires-Python: >=3.8
License-File: LICENSE
Requires-Dist: click>=8.0.0
Provides-Extra: dev
Requires-Dist: pytest>=7.0.0; extra == "dev"
Requires-Dist: pytest-cov>=4.0.0; extra == "dev"
Requires-Dist: black>=23.0.0; extra == "dev"
Requires-Dist: ruff>=0.1.0; extra == "dev"
Requires-Dist: mypy>=1.0.0; extra == "dev"
Requires-Dist: pre-commit>=3.0.0; extra == "dev"
Requires-Dist: bandit>=1.7.0; extra == "dev"
Provides-Extra: cloud
Requires-Dist: boto3>=1.26.0; extra == "cloud"
Requires-Dist: google-cloud-storage>=2.0.0; extra == "cloud"
Requires-Dist: requests>=2.28.0; extra == "cloud"
Provides-Extra: aws
Requires-Dist: boto3>=1.26.0; extra == "aws"
Requires-Dist: requests>=2.28.0; extra == "aws"
Provides-Extra: firebase
Requires-Dist: google-cloud-storage>=2.0.0; extra == "firebase"
Provides-Extra: all
Requires-Dist: boto3>=1.26.0; extra == "all"
Requires-Dist: google-cloud-storage>=2.0.0; extra == "all"
Requires-Dist: requests>=2.28.0; extra == "all"
Requires-Dist: pyyaml>=6.0.0; extra == "all"
Dynamic: license-file
